mcrp_splitters-0.2.0.data/scripts/split_input
mcrp_splitters/__init__.py
mcrp_splitters/input/main.so
mcrp_splitters/input/__init__.py
mcrp_splitters/input/cards.so
mcrp_splitters/input/blocks.so
mcrp_splitters/meshtal/meshtal.so
mcrp_splitters/meshtal/__init__.py
mcrp_splitters-0.2.0.dist-info/RECORD
mcrp_splitters-0.2.0.dist-info/WHEEL
mcrp_splitters-0.2.0.dist-info/METADATA
mcrp_splitters-0.2.0.dist-info/top_level.txt
