Metadata-Version: 2.1
Name: mcrp-splitters
Version: 0.2.0
Summary: MCNP-related packages. Splitters for text files
Home-page: UNKNOWN
Author: A. Travleev
Author-email: anton.travleev@gmail.com
License: UNKNOWN
Keywords: MCNP utilities
Platform: UNKNOWN
Classifier: Development Status :: 4 - Beta
Classifier: Environment :: Console
Classifier: Intended Audience :: Science/Research
Classifier: Intended Audience :: Education
Classifier: License :: OSI Approved :: MIT License
Classifier: Programming Language :: Python :: 2.7
Classifier: Topic :: Scientific/Engineering
Provides: mcrp_splitters
Requires-Dist: numpy
Requires-Dist: mcrp-utils
